jlight_pkg/__init__.py
jlight_jochenj-0.0.1.dist-info/LICENCE
jlight_jochenj-0.0.1.dist-info/METADATA
jlight_jochenj-0.0.1.dist-info/WHEEL
jlight_jochenj-0.0.1.dist-info/top_level.txt
jlight_jochenj-0.0.1.dist-info/RECORD
