Metadata-Version: 2.1
Name: jlight-jochenj
Version: 0.0.1
Summary: classes for accessing JLight lamps
Home-page: https://github.com/jochenjagers/jlight
Author: Jochen Jägers
Author-email: 
License: UNKNOWN
Platform: UNKNOWN
Classifier: Programming Language :: Python :: 3
Classifier: License :: OSI Approved :: MIT License
Classifier: Operating System :: OS Independent
